hats/__init__.py
hats/_version.py
hats/py.typed
hats/catalog/__init__.py
hats/catalog/catalog.py
hats/catalog/catalog_collection.py
hats/catalog/catalog_type.py
hats/catalog/partition_info.py
hats/catalog/association_catalog/__init__.py
hats/catalog/association_catalog/association_catalog.py
hats/catalog/dataset/__init__.py
hats/catalog/dataset/collection_properties.py
hats/catalog/dataset/dataset.py
hats/catalog/dataset/table_properties.py
hats/catalog/healpix_dataset/__init__.py
hats/catalog/healpix_dataset/healpix_dataset.py
hats/catalog/index/__init__.py
hats/catalog/index/index_catalog.py
hats/catalog/map/__init__.py
hats/catalog/map/map_catalog.py
hats/catalog/margin_cache/__init__.py
hats/catalog/margin_cache/margin_catalog.py
hats/inspection/__init__.py
hats/inspection/_plotting.py
hats/inspection/visualize_catalog.py
hats/io/__init__.py
hats/io/parquet_metadata.py
hats/io/paths.py
hats/io/size_estimates.py
hats/io/skymap.py
hats/io/summary_file.py
hats/io/validation.py
hats/io/file_io/__init__.py
hats/io/file_io/file_io.py
hats/io/file_io/file_pointer.py
hats/loaders/__init__.py
hats/loaders/read_hats.py
hats/pixel_math/__init__.py
hats/pixel_math/healpix_pixel.py
hats/pixel_math/healpix_pixel_convertor.py
hats/pixel_math/healpix_pixel_function.py
hats/pixel_math/healpix_shim.py
hats/pixel_math/partition_stats.py
hats/pixel_math/pixel_margins.py
hats/pixel_math/region_to_moc.py
hats/pixel_math/sparse_histogram.py
hats/pixel_math/spatial_index.py
hats/pixel_math/validators.py
hats/pixel_tree/__init__.py
hats/pixel_tree/moc_filter.py
hats/pixel_tree/moc_utils.py
hats/pixel_tree/negative_tree.py
hats/pixel_tree/pixel_alignment.py
hats/pixel_tree/pixel_alignment_types.py
hats/pixel_tree/pixel_tree.py
hats/search/__init__.py
hats/search/region_search.py
hats-0.8.1.dist-info/licenses/LICENSE
hats-0.8.1.dist-info/METADATA
hats-0.8.1.dist-info/WHEEL
hats-0.8.1.dist-info/top_level.txt
hats-0.8.1.dist-info/RECORD
