Metadata-Version: 2.4
Name: hats
Version: 0.8.1
Summary: Hierarchical Adaptive Tiling Scheme Catalog
Author-email: LINCC Frameworks <lincc-frameworks-team@lists.lsst.org>
License-Expression: BSD-3-Clause
Project-URL: Source Code, https://github.com/astronomy-commons/hats
Classifier: Development Status :: 4 - Beta
Classifier: Intended Audience :: Developers
Classifier: Intended Audience :: Science/Research
Classifier: Operating System :: OS Independent
Classifier: Programming Language :: Python
Requires-Python: >=3.11
License-File: LICENSE
Requires-Dist: aiohttp>=3.10.0
Requires-Dist: astropy>=7.0.0
Requires-Dist: cdshealpix>=0.8.0
Requires-Dist: fsspec>=2023.10.0
Requires-Dist: jinja2>=3.0.0
Requires-Dist: jproperties>=2.0.0
Requires-Dist: mocpy>=0.19.0
Requires-Dist: nested-pandas<0.7.0,>=0.6.7
Requires-Dist: numba>=0.58
Requires-Dist: numpy<3,>=2.3
Requires-Dist: pandas>=2.0
Requires-Dist: pyarrow!=19.0.0,!=21.0.0,>=14.0.1; platform_system == "Windows"
Requires-Dist: pyarrow!=19.0.0,>=14.0.1; platform_system != "Windows"
Requires-Dist: pydantic>=2.0
Requires-Dist: scipy>=1.7.2
Requires-Dist: typing-extensions>=4.3.0
Requires-Dist: universal-pathlib>=0.3.1
Provides-Extra: dev
Requires-Dist: asv[virtualenv]==0.6.5; extra == "dev"
Requires-Dist: black; extra == "dev"
Requires-Dist: jupyter; extra == "dev"
Requires-Dist: pre-commit; extra == "dev"
Requires-Dist: pylint; extra == "dev"
Requires-Dist: pytest; extra == "dev"
Requires-Dist: pytest-cov; extra == "dev"
Requires-Dist: pytest-mock; extra == "dev"
Requires-Dist: pytest-timeout; extra == "dev"
Requires-Dist: PyYAML; extra == "dev"
Provides-Extra: plotting
Requires-Dist: matplotlib>=3.10.1; extra == "plotting"
Provides-Extra: full
Requires-Dist: fsspec[full]; extra == "full"
Requires-Dist: lsst-sphgeom; (sys_platform == "darwin" or sys_platform == "linux") and extra == "full"
Requires-Dist: matplotlib>=3.10.1; extra == "full"
Dynamic: license-file
